tcm/__init__.py
tcm/catalogue.py
tcm/command.py
tcm/controller.py
tacl_catalogue_manager-1.0.2.dist-info/LICENSE
tacl_catalogue_manager-1.0.2.dist-info/METADATA
tacl_catalogue_manager-1.0.2.dist-info/WHEEL
tacl_catalogue_manager-1.0.2.dist-info/entry_points.txt
tacl_catalogue_manager-1.0.2.dist-info/top_level.txt
tacl_catalogue_manager-1.0.2.dist-info/RECORD
