Metadata-Version: 2.1
Name: tacl-catalogue-manager
Version: 1.0.2
Summary: Manager for creating TACL catalogue files
Home-page: https://github.com/ajenhl/tacl-catalogue-manager
Author: Jamie Norrish
Author-email: jamie@artefact.org.nz
License: GPLv3+
Platform: UNKNOWN
Classifier: Development Status :: 5 - Production/Stable
Classifier: Environment :: Console
Classifier: Intended Audience :: End Users/Desktop
Classifier: License :: OSI Approved :: GNU General Public License v3 or later (GPLv3+)
Classifier: Programming Language :: Python :: 3
